{
  "incident_id": "incident_20250906_224142_967",
  "timestamp": "2025-09-06T22:41:42.967004",
  "risk_type": "collision",
  "risk_score": 0.9949999999999999,
  "location": null,
  "metadata": {
    "alerts": [
      {
        "message": "BRAKE NOW! Vehicle ahead",
        "explanation": "Collision imminent! Truck close. Time to impact: 0.2s",
        "is_critical": true,
        "timestamp": "2025-09-06T22:41:42.966007"
      }
    ]
  },
  "hash": "ffa7d4f33f118cb58f62d90082753bbeacbc6495c203ab7062ac81cd47680371",
  "frame_count": 1
}