{
  "incident_id": "incident_20250907_002630_780",
  "timestamp": "2025-09-07T00:26:30.780869",
  "risk_type": "lane_change",
  "risk_score": 0.8953,
  "location": null,
  "metadata": {
    "alerts": [
      {
        "message": "CAUTION: Car changing lanes to right",
        "explanation": "Car on left rapidly moving into your lane. Prepare to brake.",
        "is_critical": true,
        "timestamp": "2025-09-07T00:26:30.780869"
      }
    ]
  },
  "hash": "721ce311119f3fdbd5161bcc315011be898d0414adf61325175dd23d4d897322",
  "frame_count": 1
}