{
  "incident_id": "incident_20250907_015321_45",
  "timestamp": "2025-09-07T01:53:21.045411",
  "risk_type": "collision",
  "risk_score": 1.0,
  "location": null,
  "metadata": {
    "alerts": [
      {
        "message": "BRAKE NOW! Vehicle ahead",
        "explanation": "Collision imminent! Car very close. Time to impact: 0.0s",
        "is_critical": true,
        "timestamp": "2025-09-07T01:53:21.045411"
      },
      {
        "message": "BRAKE NOW! Vehicle ahead",
        "explanation": "Collision imminent! Car very close. Time to impact: 0.0s",
        "is_critical": true,
        "timestamp": "2025-09-07T01:53:21.045411"
      },
      {
        "message": "BRAKE NOW! Vehicle ahead",
        "explanation": "Collision imminent! Car very close. Time to impact: 0.0s",
        "is_critical": true,
        "timestamp": "2025-09-07T01:53:21.045411"
      },
      {
        "message": "BRAKE NOW! Vehicle ahead",
        "explanation": "Collision imminent! Car very close. Time to impact: 0.0s",
        "is_critical": true,
        "timestamp": "2025-09-07T01:53:21.045411"
      },
      {
        "message": "BRAKE NOW! Vehicle ahead",
        "explanation": "Collision imminent! Car very close. Time to impact: 0.0s",
        "is_critical": true,
        "timestamp": "2025-09-07T01:53:21.045411"
      },
      {
        "message": "BRAKE NOW! Vehicle ahead",
        "explanation": "Collision imminent! Car very close. Time to impact: 0.0s",
        "is_critical": true,
        "timestamp": "2025-09-07T01:53:21.045411"
      },
      {
        "message": "CAUTION: Car changing lanes to right",
        "explanation": "Car on right making sudden lane change to the right. Be cautious.",
        "is_critical": true,
        "timestamp": "2025-09-07T01:53:21.045411"
      }
    ]
  },
  "hash": "e72d7ba93517c04aead9f4ad5530bee2bba5e907de18d6743a154b3603afc033",
  "frame_count": 1
}