{
  "incident_id": "incident_20250907_005133_102",
  "timestamp": "2025-09-07T00:51:33.102887",
  "risk_type": "lane_change",
  "risk_score": 0.95,
  "location": null,
  "metadata": {
    "alerts": [
      {
        "message": "CAUTION: Car changing lanes to left",
        "explanation": "Car on left making sudden lane change to the left. Be cautious.",
        "is_critical": true,
        "timestamp": "2025-09-07T00:51:33.102887"
      },
      {
        "message": "CAUTION: Truck changing lanes to right",
        "explanation": "Truck on right making sudden lane change to the right. Be cautious.",
        "is_critical": true,
        "timestamp": "2025-09-07T00:51:33.102887"
      }
    ]
  },
  "hash": "a08fe8825cd60dcc3980dc298e7500566257fba1763bd6761524dd41e7485745",
  "frame_count": 1
}