{
  "incident_id": "incident_20250907_002159_930",
  "timestamp": "2025-09-07T00:21:59.930711",
  "risk_type": "collision",
  "risk_score": 1.0,
  "location": null,
  "metadata": {
    "alerts": [
      {
        "message": "BRAKE NOW! Vehicle ahead",
        "explanation": "Collision imminent! Truck very close. Time to impact: 0.2s",
        "is_critical": true,
        "timestamp": "2025-09-07T00:21:59.930711"
      },
      {
        "message": "CAUTION: Truck changing lanes to right",
        "explanation": "Truck nearby making sudden lane change to the right. Be cautious.",
        "is_critical": true,
        "timestamp": "2025-09-07T00:21:59.930711"
      },
      {
        "message": "CAUTION: Truck changing lanes to right",
        "explanation": "Truck on left rapidly moving into your lane. Prepare to brake.",
        "is_critical": true,
        "timestamp": "2025-09-07T00:21:59.930711"
      },
      {
        "message": "CAUTION: Truck changing lanes to right",
        "explanation": "Truck nearby making sudden lane change to the right. Be cautious.",
        "is_critical": true,
        "timestamp": "2025-09-07T00:21:59.930711"
      },
      {
        "message": "CAUTION: Truck changing lanes to right",
        "explanation": "Truck nearby making sudden lane change to the right. Be cautious.",
        "is_critical": true,
        "timestamp": "2025-09-07T00:21:59.930711"
      }
    ]
  },
  "hash": "b5e237f8f870ec98d8ffc1ad86d6c074e0ced947173d2064bd1bda336caf807f",
  "frame_count": 1
}