{
  "incident_id": "incident_20250906_223710_298",
  "timestamp": "2025-09-06T22:37:10.297391",
  "risk_type": "collision",
  "risk_score": 0.999047619047619,
  "location": null,
  "metadata": {
    "alerts": [
      {
        "message": "BRAKE NOW! Vehicle ahead",
        "explanation": "Collision imminent! Car 163 units ahead. Time to impact: 1.0s",
        "is_critical": true,
        "timestamp": "2025-09-06T22:37:10.297391"
      }
    ]
  },
  "hash": "07bec6351b36d6053c1c7bff0cf1489a128072bea389726caf606272ff7564bd",
  "frame_count": 1
}